dagshub_api/__init__.py
dagshub_api/api_client.py
dagshub_api/configuration.py
dagshub_api/rest.py
dagshub_api/api/__init__.py
dagshub_api/api/branches_api.py
dagshub_api/api/collaborators_api.py
dagshub_api/api/commits_api.py
dagshub_api/api/content_api.py
dagshub_api/api/experiments_api.py
dagshub_api/api/issues_api.py
dagshub_api/api/releases_api.py
dagshub_api/api/repository_api.py
dagshub_api/api/user_api.py
dagshub_api/api/webhooks_api.py
dagshub_api/models/__init__.py
dagshub_api/models/assignee.py
dagshub_api/models/body.py
dagshub_api/models/closed.py
dagshub_api/models/collaborators_collaborator_body.py
dagshub_api/models/create_repo.py
dagshub_api/models/edit_experiment_post.py
dagshub_api/models/experiment_keys.py
dagshub_api/models/file.py
dagshub_api/models/files.py
dagshub_api/models/hooks_id_body.py
dagshub_api/models/issue.py
dagshub_api/models/issue_assignee.py
dagshub_api/models/issue_labels.py
dagshub_api/models/issue_milestone.py
dagshub_api/models/issues.py
dagshub_api/models/labels.py
dagshub_api/models/migrate_repo.py
dagshub_api/models/milestone.py
dagshub_api/models/patch_issue.py
dagshub_api/models/post_issue.py
dagshub_api/models/put_file.py
dagshub_api/models/repo_hooks_body.py
dagshub_api/models/state.py
dagshub_api/models/title.py
dagshub_api/models/user.py
dagshub_api/models/webhook_config.py
dagshub_api/models/webhook_events.py
test/__init__.py
test/test_assignee.py
test/test_body.py
test/test_branches_api.py
test/test_closed.py
test/test_collaborators_api.py
test/test_collaborators_collaborator_body.py
test/test_commits_api.py
test/test_content_api.py
test/test_create_repo.py
test/test_edit_experiment_post.py
test/test_experiment_keys.py
test/test_experiments_api.py
test/test_file.py
test/test_files.py
test/test_hooks_id_body.py
test/test_issue.py
test/test_issue_assignee.py
test/test_issue_labels.py
test/test_issue_milestone.py
test/test_issues.py
test/test_issues_api.py
test/test_labels.py
test/test_migrate_repo.py
dagshub_api-1.0.2.dist-info/METADATA
dagshub_api-1.0.2.dist-info/WHEEL
dagshub_api-1.0.2.dist-info/top_level.txt
dagshub_api-1.0.2.dist-info/RECORD
