Metadata-Version: 2.1
Name: dagshub-api
Version: 1.0.2
Summary: DagsHub API
Home-page: 
Author-email: 
Keywords: Swagger,DagsHub API
Requires-Dist: urllib3 (>=1.15)
Requires-Dist: six (>=1.10)
Requires-Dist: certifi
Requires-Dist: python-dateutil
